ooodev_xml/__init__.py
ooodev_xml/odxml.py
ooo_dev_xml-0.1.1.dist-info/LICENSE
ooo_dev_xml-0.1.1.dist-info/METADATA
ooo_dev_xml-0.1.1.dist-info/WHEEL
ooo_dev_xml-0.1.1.dist-info/RECORD
